[
  {"num": 1, "season": 1, "episode": 1, "title": "Episode One", "date": "2018-12-29", "url": "https://traffic.libsyn.com/secure/twinportals/Twin_Portals_Episode_One_Full_v1.2_P1P2_Balance_End_Trans_Balance.mp3?dest-id=960599"},
  {"num": 2, "season": 1, "episode": 2, "title": "Episode Two", "date": "2018-12-31", "url": "https://traffic.libsyn.com/secure/twinportals/Twin_Portals_Episode_Two_Full_v1.0.mp3?dest-id=960599"},
  {"num": 3, "season": 1, "episode": 3, "title": "Episode Three", "date": "2019-01-01", "url": "https://traffic.libsyn.com/secure/twinportals/Twin_Portals_Episode_3_Full__v1.0_-.mp3?dest-id=960599"},
  {"num": 4, "season": 1, "episode": 4, "title": "Episode Four", "date": "2019-02-18", "url": "https://traffic.libsyn.com/secure/twinportals/E4_Final_v1_-.mp3?dest-id=960599"},
  {"num": 5, "season": 1, "episode": 5, "title": "Episode Five", "date": "2019-03-30", "url": "https://traffic.libsyn.com/secure/twinportals/E5_Full_Episode_v1.0_-.mp3?dest-id=960599"},
  {"num": 6, "season": 1, "episode": 6, "title": "Episode Six", "date": "2019-04-27", "url": "https://traffic.libsyn.com/secure/twinportals/E6_Complete_-_V1.mp3?dest-id=960599"},
  {"num": 7, "season": 1, "episode": 7, "title": "Episode Seven", "date": "2019-06-01", "url": "https://traffic.libsyn.com/secure/twinportals/E7_Final_-_Full_-_1.0v.mp3?dest-id=960599"},
  {"num": 8, "season": 1, "episode": 8, "title": "Episode Eight", "date": "2019-06-29", "url": "https://traffic.libsyn.com/secure/twinportals/E8_Final_-_Final_-_1.0v_-_Medium_Quality.mp3?dest-id=960599"},
  {"num": 9, "season": 1, "episode": 9, "title": "Episode Nine", "date": "2019-07-31", "url": "https://traffic.libsyn.com/secure/twinportals/E9_Final_-_In_Progress_v1.2.1_-.mp3?dest-id=960599"},
  {"num": 10, "season": 1, "episode": 10, "title": "Episode Ten", "date": "2019-08-31", "url": "https://traffic.libsyn.com/secure/twinportals/Final_-_v1.1_-.mp3?dest-id=960599"},
  {"num": 11, "season": 1, "episode": 11, "title": "Episode Eleven", "date": "2019-09-26", "url": "https://traffic.libsyn.com/secure/twinportals/D11_Final_-_In_Progress_v1.5_-.mp3?dest-id=960599"},
  {"num": 12, "season": 1, "episode": 12, "title": "Episode Twelve", "date": "2019-10-20", "url": "https://traffic.libsyn.com/secure/twinportals/E12_Final_-_V1.7_-.mp3?dest-id=960599"},
  {"num": 13, "season": 1, "episode": 13, "title": "Episode Thirteen", "date": "2019-11-30", "url": "https://traffic.libsyn.com/secure/twinportals/Final_-_1.4_-_Finished.mp3?dest-id=960599"},
  {"num": 14, "season": 1, "episode": 14, "title": "Episode Fourteen", "date": "2019-12-29", "url": "https://traffic.libsyn.com/secure/twinportals/E14_-_Final_-_v1.3_-.mp3?dest-id=960599"},
  {"num": 15, "season": 1, "episode": 15, "title": "Episode Fifteen", "date": "2020-01-19", "url": "https://traffic.libsyn.com/secure/twinportals/Final_v1.2_-.mp3?dest-id=960599"},
  {"num": 16, "season": 1, "episode": 16, "title": "Episode Sixteen", "date": "2020-02-18", "url": "https://traffic.libsyn.com/secure/twinportals/Final_-_v1.2_-_Finished_Product.mp3?dest-id=960599"},
  {"num": 17, "season": 1, "episode": 17, "title": "Episode Seventeen", "date": "2020-03-22", "url": "https://traffic.libsyn.com/secure/twinportals/E17_-_Final_Cut_-_v1.1_-_Finished.mp3?dest-id=960599"},
  {"num": 18, "season": 1, "episode": 18, "title": "Episode Eighteen", "date": "2020-04-28", "url": "https://traffic.libsyn.com/secure/twinportals/E18_-_Good_Version_-_Final_-_v1.0_-.mp3?dest-id=960599"},
  {"num": 19, "season": 1, "episode": 19, "title": "Episode Nineteen", "date": "2020-05-16", "url": "https://traffic.libsyn.com/secure/twinportals/E19_-_Finished_-_v1.2_-_Final_Mix_Fixed.mp3?dest-id=960599"},
  {"num": 20, "season": 1, "episode": 20, "title": "Episode Twenty", "date": "2021-02-01", "url": "https://traffic.libsyn.com/secure/twinportals/E20_-_v2.0_-_Final.mp3?dest-id=960599"},
  {"num": 21, "season": 1, "episode": 21, "title": "Episode Twenty One", "date": "2021-03-28", "url": "https://traffic.libsyn.com/secure/twinportals/E21_-_Final_Product_-_v1.0_-.mp3?dest-id=960599"},
  {"num": 22, "season": 1, "episode": 22, "title": "Episode Twenty Two", "date": "2021-04-24", "url": "https://traffic.libsyn.com/secure/twinportals/E22_-_Final_-.mp3?dest-id=960599"},
  {"num": 23, "season": 1, "episode": 23, "title": "Episode Twenty Three", "date": "2021-05-26", "url": "https://traffic.libsyn.com/secure/twinportals/E23_-_v1.0_-_Final.mp3?dest-id=960599"},
  {"num": 24, "season": 1, "episode": 24, "title": "Episode Twenty Four", "date": "2021-06-25", "url": "https://traffic.libsyn.com/secure/twinportals/E24_-_Final_-_v1.1_-.mp3?dest-id=960599"},
  {"num": 25, "season": 1, "episode": 25, "title": "Episode Twenty Five", "date": "2021-07-22", "url": "https://traffic.libsyn.com/secure/twinportals/E25_-_Final_-_v1.0_-.mp3?dest-id=960599"},
  {"num": 26, "season": 1, "episode": 26, "title": "Episode Twenty Six", "date": "2021-08-24", "url": "https://traffic.libsyn.com/secure/twinportals/E26_-_Final_-_V1.0_-.mp3?dest-id=960599"},
  {"num": 27, "season": 1, "episode": 27, "title": "Episode Twenty Seven", "date": "2021-09-27", "url": "https://traffic.libsyn.com/secure/twinportals/E27_-_Final_-_V1.0.mp3?dest-id=960599"},
  {"num": 28, "season": 1, "episode": 28, "title": "Episode Twenty Eight", "date": "2021-10-30", "url": "https://traffic.libsyn.com/secure/twinportals/E28_-_Finished_-_v1.2_-.mp3?dest-id=960599"},
  {"num": 29, "season": 1, "episode": 29, "title": "Episode Twenty Nine", "date": "2021-11-28", "url": "https://traffic.libsyn.com/secure/twinportals/E29_-_Final_-_v0.2_-.mp3?dest-id=960599"},
  {"num": 30, "season": 1, "episode": 30, "title": "Episode Thirty", "date": "2021-12-26", "url": "https://traffic.libsyn.com/secure/twinportals/E30_-_Final_-_v1.0_-.mp3?dest-id=960599"},
  {"num": 31, "season": 2, "episode": 1, "title": "Episode Thirty One (S02E01)", "date": "2022-02-28", "url": "https://traffic.libsyn.com/secure/twinportals/E31_-_Final_-_v1.0_-.mp3?dest-id=960599"},
  {"num": 32, "season": 2, "episode": 2, "title": "Episode Thirty Two (S02E02)", "date": "2022-03-27", "url": "https://traffic.libsyn.com/secure/twinportals/E32_-_Final_-_v1.1_-.mp3?dest-id=960599"},
  {"num": 33, "season": 2, "episode": 3, "title": "Episode Thirty Three (S02E03)", "date": "2022-05-25", "url": "https://traffic.libsyn.com/secure/twinportals/E33_-_Final_Mixdown_v1.1.mp3?dest-id=960599"},
  {"num": 34, "season": 2, "episode": 4, "title": "Episode Thirty Four (S02E04)", "date": "2022-06-15", "url": "https://traffic.libsyn.com/secure/twinportals/E34_-_Final_-_v1.0_-.mp3?dest-id=960599"},
  {"num": 35, "season": 2, "episode": 5, "title": "Episode Thirty Five (S02E05)", "date": "2022-07-24", "url": "https://traffic.libsyn.com/secure/twinportals/E35_-_Final_-_V1.0_-.mp3?dest-id=960599"},
  {"num": 36, "season": 2, "episode": 6, "title": "Episode Thirty Six (S02E06)", "date": "2022-08-24", "url": "https://traffic.libsyn.com/secure/twinportals/E36_-_Finished_-_v1.0.mp3?dest-id=960599"},
  {"num": 37, "season": 2, "episode": 7, "title": "Episode Thirty Seven (S02E07)", "date": "2022-09-25", "url": "https://traffic.libsyn.com/secure/twinportals/E37_-_Final_-_v1.0_-.mp3?dest-id=960599"},
  {"num": 38, "season": 2, "episode": 8, "title": "Episode Thirty Eight (S02E08)", "date": "2022-10-25", "url": "https://traffic.libsyn.com/secure/twinportals/E38_-_Final_-_v1.1_-.mp3?dest-id=960599"},
  {"num": 39, "season": 2, "episode": 9, "title": "Episode Thirty Nine (S02E09)", "date": "2022-11-29", "url": "https://traffic.libsyn.com/secure/twinportals/E39_-_Final_-_v1.0_-_.mp3?dest-id=960599"},
  {"num": 40, "season": 2, "episode": 10, "title": "Episode Forty (S02E10)", "date": "2022-12-22", "url": "https://traffic.libsyn.com/secure/twinportals/E40_Final.mp3?dest-id=960599"},
  {"num": 41, "season": 2, "episode": 11, "title": "Episode Forty One (S02E11)", "date": "2023-01-27", "url": "https://traffic.libsyn.com/secure/twinportals/E41_Live_Final_v1.2-004.mp3?dest-id=960599"},
  {"num": 42, "season": 2, "episode": 12, "title": "Episode Forty Two (S02E12)", "date": "2023-02-26", "url": "https://traffic.libsyn.com/secure/twinportals/E42_10.mp3?dest-id=960599"},
  {"num": 43, "season": 2, "episode": 13, "title": "Episode Forty Three LIVE! (S02E13)", "date": "2023-03-26", "url": "https://traffic.libsyn.com/secure/twinportals/E43_Live_-_Final_v1.0.mp3?dest-id=960599"},
  {"num": 44, "season": 2, "episode": 14, "title": "Episode Forty Four (S02E14)", "date": "2023-04-30", "url": "https://traffic.libsyn.com/secure/twinportals/E44_v1.0.mp3?dest-id=960599"},
  {"num": 45, "season": 2, "episode": 15, "title": "Episode Forty Five (S02E15)", "date": "2023-05-22", "url": "https://traffic.libsyn.com/secure/twinportals/E45_-_Final.mp3?dest-id=960599"},
  {"num": 46, "season": 2, "episode": 16, "title": "Episode Forty Six LIVE! (S02E16)", "date": "2023-06-28", "url": "https://traffic.libsyn.com/secure/twinportals/E46_-_Final.mp3?dest-id=960599"},
  {"num": 47, "season": 2, "episode": 17, "title": "Episode Forty Seven (S02E17)", "date": "2023-07-24", "url": "https://traffic.libsyn.com/secure/twinportals/E47_-_Final-003.mp3?dest-id=960599"},
  {"num": 48, "season": 2, "episode": 18, "title": "Episode Forty Eight LIVE (S02E18)", "date": "2023-08-31", "url": "https://traffic.libsyn.com/secure/twinportals/E48_-_Final-001.mp3?dest-id=960599"},
  {"num": 49, "season": 2, "episode": 19, "title": "Episode Forty Nine (S02E19)", "date": "2023-09-28", "url": "https://traffic.libsyn.com/secure/twinportals/E-49_-_Final.mp3?dest-id=960599"},
  {"num": 50, "season": 2, "episode": 20, "title": "Episode Fifty! (S02E20)", "date": "2023-10-29", "url": "https://traffic.libsyn.com/secure/twinportals/E50_-_Final_Corrected.mp3?dest-id=960599"},
  {"num": 51, "season": 2, "episode": 21, "title": "Episode Fifty One (S02E21)", "date": "2023-11-30", "url": "https://traffic.libsyn.com/secure/twinportals/E51_-_Final.mp3?dest-id=960599"},
  {"num": 52, "season": 2, "episode": 22, "title": "Episode Fifty Two LIVE (S02E22)", "date": "2023-12-31", "url": "https://traffic.libsyn.com/secure/twinportals/E052_-_Final.mp3?dest-id=960599"},
  {"num": 53, "season": 2, "episode": 23, "title": "Episode Fifty Three (S02E23)", "date": "2024-01-31", "url": "https://traffic.libsyn.com/secure/twinportals/E053_-_Final.mp3?dest-id=960599"},
  {"num": 54, "season": 2, "episode": 24, "title": "Episode Fifty Four (S02E24)", "date": "2024-02-27", "url": "https://traffic.libsyn.com/secure/twinportals/E054_-_Final.mp3?dest-id=960599"},
  {"num": 55, "season": 2, "episode": 25, "title": "Episode Fifty Five LIVE (S02E25)", "date": "2024-03-24", "url": "https://traffic.libsyn.com/secure/twinportals/E055_LIVE_-_Final_v1.0.mp3?dest-id=960599"},
  {"num": 56, "season": 2, "episode": 26, "title": "Episode Fifty Six (S02E26)", "date": "2024-04-30", "url": "https://traffic.libsyn.com/secure/twinportals/E056_-_v1.0.mp3?dest-id=960599"},
  {"num": 57, "season": 2, "episode": 27, "title": "Episode Fifty Seven (S02E27)", "date": "2024-05-26", "url": "https://traffic.libsyn.com/secure/twinportals/E057_-_Final.mp3?dest-id=960599"},
  {"num": 58, "season": 2, "episode": 28, "title": "Episode Fifty Eight (S02E28)", "date": "2024-06-30", "url": "https://traffic.libsyn.com/secure/twinportals/E58_-_Final_v1.0.mp3?dest-id=960599"},
  {"num": 59, "season": 2, "episode": 29, "title": "Episode Fifty Nine LIVE! (S02E29)", "date": "2024-07-27", "url": "https://traffic.libsyn.com/secure/twinportals/E59_live_-_Final.mp3?dest-id=960599"},
  {"num": 60, "season": 2, "episode": 30, "title": "Episode Sixty (S02E30)", "date": "2024-08-29", "url": "https://traffic.libsyn.com/secure/twinportals/E060_-_Final.mp3?dest-id=960599"},
  {"num": 61, "season": 2, "episode": 31, "title": "Episode Sixty One (S02E31)", "date": "2024-09-27", "url": "https://traffic.libsyn.com/secure/twinportals/E061_-_Final.mp3?dest-id=960599"},
  {"num": 62, "season": 2, "episode": 32, "title": "Episode Sixty Two LIVE! (S02E32)", "date": "2024-10-30", "url": "https://traffic.libsyn.com/secure/twinportals/E062_-_Final.mp3?dest-id=960599"},
  {"num": 63, "season": 2, "episode": 33, "title": "Episode Sixty Three (S02E33)", "date": "2024-11-28", "url": "https://traffic.libsyn.com/secure/twinportals/E063_-_Final.mp3?dest-id=960599"},
  {"num": 64, "season": 2, "episode": 34, "title": "Episode Sixty Four LIVE! (S02E34)", "date": "2024-12-30", "url": "https://traffic.libsyn.com/secure/twinportals/E064_-_Final.mp3?dest-id=960599"},
  {"num": 65, "season": 2, "episode": 35, "title": "Episode Sixty Five (S02E35)", "date": "2025-01-30", "url": "https://traffic.libsyn.com/secure/twinportals/E065_-_Final.mp3?dest-id=960599"},
  {"num": 66, "season": 2, "episode": 36, "title": "Episode Sixty Six (S02E36)", "date": "2025-02-27", "url": "https://traffic.libsyn.com/secure/twinportals/E066_-_Final.mp3?dest-id=960599"},
  {"num": 67, "season": 2, "episode": 37, "title": "Episode Sixty Seven LIVE (S02E37)", "date": "2025-03-30", "url": "https://traffic.libsyn.com/secure/twinportals/E067_-_Final.mp3?dest-id=960599"},
  {"num": 68, "season": 2, "episode": 38, "title": "Episode Sixty Eight - Season Two Finale! (S02E38)", "date": "2025-05-11", "url": "https://traffic.libsyn.com/secure/twinportals/E068_-_Final-002.mp3?dest-id=960599"},
  {"num": 69, "season": 3, "episode": 1, "title": "S3E01 - Re-Introductions", "date": "2025-05-31", "url": "https://traffic.libsyn.com/secure/twinportals/Twin_Portals_-_S3E01_-_Final_v1.0.mp3?dest-id=960599"},
  {"num": 70, "season": 3, "episode": 2, "title": "S3E02 - How We've Funded Our Projects", "date": "2025-06-30", "url": "https://traffic.libsyn.com/secure/twinportals/Twin_Portals_-_S3E02_-_Audio_Only_v0.1.mp3?dest-id=960599"},
  {"num": 71, "season": 3, "episode": 3, "title": "S3E03 - Parenthood, ft. Beth and Justin", "date": "2025-07-29", "url": "https://traffic.libsyn.com/secure/twinportals/Twin_Portals_-_S3E03_-_Parenthood_-_v1.1-001.mp3?dest-id=960599"},
  {"num": 72, "season": 3, "episode": 4, "title": "S3E04 - Twin Portals Live at ExcaliburCon", "date": "2025-08-31", "url": "https://traffic.libsyn.com/secure/twinportals/S03E04_-_ExCon-001.mp3?dest-id=960599"},
  {"num": 73, "season": 3, "episode": 5, "title": "S3E05 - LIVE at Studio 4!", "date": "2025-09-30", "url": "https://traffic.libsyn.com/secure/twinportals/Twin_Portals_-_S3E5_-_Sept_Live_Show_-_Final_v1.0_001.mp3?dest-id=960599"},
  {"num": 74, "season": 3, "episode": 6, "title": "S3E06 - The Producers Took This One Off", "date": "2025-10-31", "url": "https://traffic.libsyn.com/secure/twinportals/TP_S3E6.mp3?dest-id=960599"},
  {"num": 75, "season": 3, "episode": 7, "title": "S3E07 - Femmes, Thems, and Searching for Gems", "date": "2025-11-26", "url": "https://traffic.libsyn.com/secure/twinportals/TP_S03E07_-_Femmes_Thems_Gems-002.mp3?dest-id=960599"},
  {"num": 76, "season": 3, "episode": 8, "title": "S3E08 - DM Sessions", "date": "2025-12-25", "url": "https://traffic.libsyn.com/secure/twinportals/DMSessions_-_Audio_Only_-_V1.0_-_Final.mp3?dest-id=960599"},
  {"num": 77, "season": 3, "episode": 9, "title": "S3E09 - The January Live Show at Studio 4!", "date": "2026-01-16", "url": "https://traffic.libsyn.com/secure/twinportals/TPS03E09_-_January_Live_Show_-_Audio_Only_-_v1.0.mp3?dest-id=960599"},
  {"num": 78, "season": 3, "episode": 10, "title": "S3E10 - Painting Minis and Making Plans", "date": "2026-02-28", "url": "https://traffic.libsyn.com/secure/twinportals/S3E10_-_MiniPainting2_-_Final_v1.0.mp3?dest-id=960599"}
]
